mahadi_humans/__init__.py
mahadi_humans/battery.py
mahadi_humans-0.0.2.dist-info/METADATA
mahadi_humans-0.0.2.dist-info/WHEEL
mahadi_humans-0.0.2.dist-info/licenses/LICENSE
mahadi_humans-0.0.2.dist-info/RECORD
