Metadata-Version: 2.4
Name: mahadi_humans
Version: 0.0.2
Summary: collection of biblical humans and their family relations
Project-URL: Homepage, https://github.com/MariyaSha/humans
Project-URL: Issues, https://github.com/MariyaSha/humans
Author-email: Mariya Sha <mariya@pythonsimplified.org>
License-File: LICENSE
Classifier: License :: OSI Approved :: GNU General Public License v3 (GPLv3)
Classifier: Operating System :: OS Independent
Classifier: Programming Language :: Python :: 3
Requires-Python: >=3.0
